modelicalang/__init__.py
modelicalang/_backend.py
modelicalang/exceptions.py
modelicalang/py.typed
modelicalang/v3_4.py
modelicalang/v3_5.py
modelicalang-0.1.0a2.dist-info/LICENSE
modelicalang-0.1.0a2.dist-info/METADATA
modelicalang-0.1.0a2.dist-info/WHEEL
modelicalang-0.1.0a2.dist-info/RECORD
